quantstats_lumi/__init__.py
quantstats_lumi/plots.py
quantstats_lumi/report.html
quantstats_lumi/reports.py
quantstats_lumi/stats.py
quantstats_lumi/utils.py
quantstats_lumi/version.py
quantstats_lumi/_plotting/__init__.py
quantstats_lumi/_plotting/core.py
quantstats_lumi/_plotting/wrappers.py
quantstats_lumi-1.1.0.dist-info/licenses/LICENSE.txt
quantstats_lumi-1.1.0.dist-info/METADATA
quantstats_lumi-1.1.0.dist-info/WHEEL
quantstats_lumi-1.1.0.dist-info/entry_points.txt
quantstats_lumi-1.1.0.dist-info/top_level.txt
quantstats_lumi-1.1.0.dist-info/RECORD
