Metadata-Version: 2.4
Name: quantstats-lumi
Version: 1.1.0
Summary: Portfolio analytics for quants
Home-page: https://github.com/Lumiwealth/quantstats_lumi
Author: Robert Grzesik (Lumiwealth)
Author-email: rob@lumiwealth.com
License: Apache Software License
Keywords: quant algotrading algorithmic-trading quantitative-trading
Platform: any
Classifier: License :: OSI Approved :: Apache Software License
Classifier: Development Status :: 5 - Production/Stable
Classifier: Operating System :: OS Independent
Classifier: Intended Audience :: Developers
Classifier: Intended Audience :: Financial and Insurance Industry
Classifier: Intended Audience :: Science/Research
Classifier: Topic :: Office/Business :: Financial
Classifier: Topic :: Office/Business :: Financial :: Investment
Classifier: Topic :: Software Development :: Libraries
Classifier: Topic :: Software Development :: Libraries :: Python Modules
Classifier: Topic :: Scientific/Engineering
Classifier: Topic :: Scientific/Engineering :: Information Analysis
Classifier: Topic :: Scientific/Engineering :: Mathematics
Classifier: Programming Language :: Python :: 3.6
Classifier: Programming Language :: Python :: 3.7
Classifier: Programming Language :: Python :: 3.8
Classifier: Programming Language :: Python :: 3.9
Requires-Python: >=3.6
License-File: LICENSE.txt
Requires-Dist: pandas>=2.2.0
Requires-Dist: numpy>=1.26.4
Requires-Dist: seaborn>=0.13.2
Requires-Dist: matplotlib>=3.0.0
Requires-Dist: scipy>=1.2.0
Requires-Dist: tabulate>=0.8.0
Requires-Dist: yfinance>=0.2.36
Requires-Dist: python-dateutil>=2.0
Requires-Dist: ipython>=8.22.2
Requires-Dist: pytest
Dynamic: author
Dynamic: author-email
Dynamic: classifier
Dynamic: description
Dynamic: description-content-type
Dynamic: home-page
Dynamic: keywords
Dynamic: license
Dynamic: license-file
Dynamic: platform
Dynamic: requires-dist
Dynamic: requires-python
Dynamic: summary
